cressp/__init__.py
cressp/__main__.py
cressp/cross_reactivity_prediction/__init__.py
cressp/cross_reactivity_prediction/b_cell_cross_reactivity_prediction.py
cressp/cross_reactivity_prediction/t_cell_cross_reactivity_prediction.py
cressp/data/__init__.py
cressp/data/blosum62.tsv.gz
cressp/data/parse_data.py
cressp/structural_property_estimation/__init__.py
cressp/structural_property_estimation/main.py
cressp/web_application/__init__.py
cressp/web_application/cressp_web_viewer.html
cressp/web_application/prepare_data.py
cressp-0.2.10.dist-info/LICENSE
cressp-0.2.10.dist-info/METADATA
cressp-0.2.10.dist-info/WHEEL
cressp-0.2.10.dist-info/entry_points.txt
cressp-0.2.10.dist-info/top_level.txt
cressp-0.2.10.dist-info/RECORD
