Metadata-Version: 2.1
Name: cressp
Version: 0.2.10
Summary: a program to find cross-reactive epitopes with structural information from known protein structures.
Home-page: https://github.com/ahs2202/cressp
Author: Hyunsu An
Author-email: ahs2202@gm.gist.ac.kr
License: GPLv3
Platform: UNKNOWN
License-File: LICENSE
Requires-Dist: tensorflow (>=2.3.0)
Requires-Dist: biobookshelf (>=0.1.28)
Requires-Dist: mhcflurry (>=2.0.2)
Requires-Dist: pandas (>=1.2.0)
